README.md
setup.py
itksop/__init__.py
itksop.egg-info/PKG-INFO
itksop.egg-info/SOURCES.txt
itksop.egg-info/dependency_links.txt
itksop.egg-info/requires.txt
itksop.egg-info/top_level.txt
itksop/Hybrid/__init__.py
itksop/Hybrid/page1_HybridAssembly.py
itksop/Hybrid/page2_HybridMetrology.py
itksop/Hybrid/page3_HybridWirebonding.py
itksop/Hybrid/page4_HybridElectricalTest.py
itksop/Hybrid/page5_HybridBurnIn.py
itksop/Module/__init__.py
itksop/Module/page1_ModuleAssembly.py
itksop/Module/page2_ModuleMetrology.py
itksop/Module/page3_ModuleWirebonding.py
itksop/Module/page4_ModuleElectricalTest.py
itksop/Module/page5_ModuleThermalCycle.py
itksop/Overview/__init__.py
itksop/Overview/page1_Home.py
itksop/Overview/page2_Inventory.py
itksop/Overview/page3_Monitoring.py
itksop/Overview/page4_Report.py
itksop/Shipment/__init__.py
itksop/Shipment/page1_Reception.py
itksop/Shipment/page2_Sending.py