Metadata-Version: 1.1
Name: itksop
Version: 2.0.2
Summary: ATLAS ITk SOP
Home-page: UNKNOWN
Author: Shudong Wang
Author-email: wangsd@ihep.ac.cn
License: MIT
Platform: UNKNOWN
Classifier: Programming Language :: Python :: 3
Classifier: License :: OSI Approved :: MIT License
Classifier: Operating System :: OS Independent
